Workbook

Sheet Simulator
A1: Pricing & Campaign Simulator — India Gate Everyday 5kg | Blinkit
A2: OLS elasticities | Anchored to last 30-day actuals (Apr 2026) | Day-level model
A4: ▶ INPUTS (Yellow cells are user-editable)
A5: SKU ID | B5: SKU | C5: Current PTC (₹) | D5: PTC Change (%) | E5: Simulated PTC (₹) | F5: Current Comp PTC | G5: Simulated RPI | H5: Current OSA | I5: Simulated OSA | J5: Current Avg Position (National) | K5: Simulated Avg Position (National) | L5: Elasticity (ε) | M5: osa coeff | N5: position coeff
A6: 10117961 | B6: IG Everyday 5 | C6: 355.69 | D6: -10 | E6: =C6*(1+D6/100) -> 320.121 | F6: 347.73 | G6: =E6/F6 -> 0.92060219 | H6: 0.78 | I6: 0.78 | J6: 3.21 | K6: 3.21 | L6: 0.396466 | M6: 0.03 | N6: -0.000552 | O6: =E20-F20 -> -0.23
A7: 10000195 | B7: IG Feast Rozzana 1 | C7: 99.88 | D7: 0 | E7: =C7*(1+D7/100) -> 99.88 | F7: 92.78 | G7: =E7/F7 -> 1.0765251 | H7: 0.78 | I7: 0.78 | J7: 4.55 | K7: 4.55 | L7: -0.446434 | M7: 0.03 | N7: 0.006049 | O7: =E21-F21 -> -0.45
A8: 10006061 | B8: IG Feast Rozzana 5 | C8: 439.22 | D8: 0 | E8: =C8*(1+D8/100) -> 439.22 | F8: 431.53 | G8: =E8/F8 -> 1.0178203 | H8: 0.78 | I8: 0.78 | J8: 6.17 | K8: 6.17 | L8: 0.416862 | M8: 0.03 | N8: 0.001196 | O8: =E22-F22 -> 0.23
A9: 10006305 | B9: IG Mini Mogra 10 | C9: 607.94 | D9: 0 | E9: =C9*(1+D9/100) -> 607.94 | F9: 595.37 | G9: =E9/F9 -> 1.0211129 | H9: 0.78 | I9: 0.78 | J9: 4.86 | K9: 4.86 | L9: -0.543019 | M9: 0.03 | N9: 0.000274 | O9: =E23-F23 -> 0.19
A10: 10012362 | B10: IG Mini Mogra 5 | C10: 321.77 | D10: 0 | E10: =C10*(1+D10/100) -> 321.77 | F10: 303.14 | G10: =E10/F10 -> 1.0614568 | H10: 0.78 | I10: 0.78 | J10: 1 | K10: 1 | L10: 0.3535641 | M10: 0.03 | N10: -1.629212e-12 | O10: =E24-F24 -> -0.06
A11: 10046799 | B11: IG Mini Mogra II 10 | C11: 496.42 | D11: 0 | E11: =C11*(1+D11/100) -> 496.42 | F11: 501.64 | G11: =E11/F11 -> 0.98959413 | H11: 0.78 | I11: 0.78 | J11: 4.86 | K11: 4.86 | L11: 0.767514 | M11: 0.03 | N11: 0.000431 | O11: =E25-F25 -> -0.06
A12: 10030412 | B12: IG Mogra 10 | C12: 689.26 | D12: 0 | E12: =C12*(1+D12/100) -> 689.26 | F12: 656.39 | G12: =E12/F12 -> 1.0500769 | H12: 0.78 | I12: 0.78 | J12: 0.07 | K12: 0.07 | L12: 0.54432 | M12: 0.03 | N12: -0.029982 | O12: =E26-F26 -> -0.39
A13: 10000196 | B13: IG Mogra 5 | C13: 358.7 | D13: 0 | E13: =C13*(1+D13/100) -> 358.7 | F13: 337.45 | G13: =E13/F13 -> 1.0629723 | H13: 0.78 | I13: 0.78 | J13: 3.57 | K13: 3.57 | L13: -0.006453 | M13: 0.03 | N13: 0.015619 | O13: =E27-F27 -> 0.06
A14: 10002013 | B14: IG Super 5 | C14: 745.3 | D14: 0 | E14: =C14*(1+D14/100) -> 745.3 | F14: 735.72 | G14: =E14/F14 -> 1.0130213 | H14: 0.78 | I14: 0.78 | J14: 6.76 | K14: 6.76 | L14: -0.514138 | M14: 0.03 | N14: -0.00794 | O14: =E28-F28 -> 0
B16: ) | O16: Inputs
R17: RPI
A18: SKU ID | B18: SKU | C18: Period | D18: Scenario | E18: Avg_Daily_Volume (Current) | F18: Avg_Daily_Volume (Simulated) | G18: Volume lost Δ | H18: VTM Gain | I18: Final Avg_Daily_Volume (Simulated) | J18: Monthly_Volume (Current) | K18: Final Monthly_Volume (nextmonth (Simulated) | L18: Volume Δ% | M18: Revenue (₹) (Current) | N18: Revenue (₹) (Simulated) | O18: Revenue Δ (₹) | P18: Revenue Δ % | R18: Avail
A19: 10117961 | B19: IG Everyday 5 | C19: 1 Month | D19: =IF(E6=C6,IF(N6=L6,"No Change","Budget Change Only"),IF(N6=L6,"PTC Change Only","PTC + Others")) -> PTC + Others | E19: 2469.65 | F19: =ROUND(E19*(E6/C6)^L6*(K6/J6)^N6*(I6/H6)^M6,0) -> 2369 | G19: =E19-F19 -> 100.65 | H19: =SUMPRODUCT(-$G$19:$G$27, VTM!B$2:B$10) -> 0.18833709 | I19: =F19+H19 -> 2369.1883 | J19: =E19*30 -> 74089.5 | K19: =I19*31 -> 73444.838 | L19: =IF(J19=0,0,(K19-J19)/J19) -> -0.0087011189 | M19: =J19*C6 -> 26352894 | N19: =K19*E6 -> 23511235 | O19: =N19-M19 -> -2841659.1 | P19: =O19/N19 -> -0.12086388 | R19: Budget
A20: 10000195 | B20: IG Feast Rozzana 1 | C20: 1 Month | D20: =IF(E7=C7,IF(N7=L7,"No Change","Budget Change Only"),IF(N7=L7,"PTC Change Only","PTC + Others")) -> Budget Change Only | E20: 1784.77 | F20: =ROUND(E20*((E7/C7)^L7)*((K7/J7)^N7)*((I7/H7)^M7),0) -> 1785 | G20: =E20-F20 -> -0.23 | H20: =SUMPRODUCT(-$G$19:$G$27, VTM!C$2:C$10) -> -7.4674528 | I20: =F20+H20 -> 1777.5325 | J20: =E20*30 -> 53543.1 | K20: =I20*31 -> 55103.509 | L20: =IF(J20=0,0,(K20-J20)/J20) -> 0.029143045 | M20: =J20*C7 -> 5347884.8 | N20: =K20*E7 -> 5503738.5 | O20: =N20-M20 -> 155853.65 | P20: =O20/N20 -> 0.028317779
A21: 10006061 | B21: IG Feast Rozzana 5 | C21: 1 Month | D21: =IF(E8=C8,IF(N8=L8,"No Change","Budget Change Only"),IF(N8=L8,"PTC Change Only","PTC + Others")) -> Budget Change Only | E21: 876.55 | F21: =ROUND(E21*((E8/C8)^L8)*((K8/J8)^N8)*((I8/H8)^M8),0) -> 877 | G21: =E21-F21 -> -0.45 | H21: =SUMPRODUCT(-$G$19:$G$27, VTM!D$2:D$10) -> -11.716055 | I21: =F21+H21 -> 865.28394 | J21: =E21*30 -> 26296.5 | K21: =I21*31 -> 26823.802 | L21: =IF(J21=0,0,(K21-J21)/J21) -> 0.020052185 | M21: =J21*C8 -> 11549949 | N21: =K21*E8 -> 11781550 | O21: =N21-M21 -> 231601.71 | P21: =O21/N21 -> 0.019658 | Q21: how do I validate simulation results
A22: 10006305 | B22: IG Mini Mogra 10 | C22: 1 Month | D22: =IF(E9=C9,IF(N9=L9,"No Change","Budget Change Only"),IF(N9=L9,"PTC Change Only","PTC + Others")) -> Budget Change Only | E22: 257.23 | F22: =ROUND(E22*((E9/C9)^L9)*((K9/J9)^N9)*((I9/H9)^M9),0) -> 257 | G22: =E22-F22 -> 0.23 | H22: =SUMPRODUCT(-$G$19:$G$27, VTM!E$2:E$10) -> -0.24838758 | I22: =F22+H22 -> 256.75161 | J22: =E22*30 -> 7716.9 | K22: =I22*31 -> 7959.3 | L22: =IF(J22=0,0,(K22-J22)/J22) -> 0.031411575 | M22: =J22*C9 -> 4691412.2 | N22: =K22*E9 -> 4838776.8 | O22: =N22-M22 -> 147364.65 | P22: =O22/N22 -> 0.030454938 | Q22: is curr method to calculate impact of other variable other than price is corect?
A23: 10012362 | B23: IG Mini Mogra 5 | C23: 1 Month | D23: =IF(E10=C10,IF(N10=L10,"No Change","Budget Change Only"),IF(N10=L10,"PTC Change Only","PTC + Others")) -> Budget Change Only | E23: 807.19 | F23: =ROUND(E23*((E10/C10)^L10)*((K10/J10)^N10)*((I10/H10)^M10),0) -> 807 | G23: =E23-F23 -> 0.19 | H23: =SUMPRODUCT(-$G$19:$G$27, VTM!F$2:F$10) -> -1.3221463 | I23: =F23+H23 -> 805.67785 | J23: =E23*30 -> 24215.7 | K23: =I23*31 -> 24976.013 | L23: =IF(J23=0,0,(K23-J23)/J23) -> 0.031397542 | M23: =J23*C10 -> 7791885.8 | N23: =K23*E10 -> 8036531.9 | O23: =N23-M23 -> 244646.06 | P23: =O23/N23 -> 0.030441746 | Q23: do I need to do baseline forecasting for future months?
A24: 10046799 | B24: IG Mini Mogra II 10 | C24: 1 Month | D24: =IF(E11=C11,IF(N11=L11,"No Change","Budget Change Only"),IF(N11=L11,"PTC Change Only","PTC + Others")) -> Budget Change Only | E24: 862.94 | F24: =ROUND(E24*((E11/C11)^L11)*((K11/J11)^N11)*((I11/H11)^M11),0) -> 863 | G24: =E24-F24 -> -0.06 | H24: =SUMPRODUCT(-$G$19:$G$27, VTM!G$2:G$10) -> -0.95428448 | I24: =F24+H24 -> 862.04572 | J24: =E24*30 -> 25888.2 | K24: =I24*31 -> 26723.417 | L24: =IF(J24=0,0,(K24-J24)/J24) -> 0.032262466 | M24: =J24*C11 -> 12851420 | N24: =K24*E11 -> 13266039 | O24: =N24-M24 -> 414618.51 | P24: =O24/N24 -> 0.031254131 | Q24: VTM
A25: 10030412 | B25: IG Mogra 10 | C25: 1 Month | D25: =IF(E12=C12,IF(N12=L12,"No Change","Budget Change Only"),IF(N12=L12,"PTC Change Only","PTC + Others")) -> Budget Change Only | E25: 248.94 | F25: =ROUND(E25*((E12/C12)^L12)*((K12/J12)^N12)*((I12/H12)^M12),0) -> 249 | G25: =E25-F25 -> -0.06 | H25: =SUMPRODUCT(-$G$19:$G$27, VTM!H$2:H$10) -> -0.21815714 | I25: =F25+H25 -> 248.78184 | J25: =E25*30 -> 7468.2 | K25: =I25*31 -> 7712.2371 | L25: =IF(J25=0,0,(K25-J25)/J25) -> 0.032676834 | M25: =J25*C12 -> 5147531.5 | N25: =K25*E12 -> 5315736.6 | O25: =N25-M25 -> 168205.03 | P25: =O25/N25 -> 0.031642846
A26: 10000196 | B26: IG Mogra 5 | C26: 1 Month | D26: =IF(E13=C13,IF(N13=L13,"No Change","Budget Change Only"),IF(N13=L13,"PTC Change Only","PTC + Others")) -> Budget Change Only | E26: 963.61 | F26: =ROUND(E26*((E13/C13)^L13)*((K13/J13)^N13)*((I13/H13)^M13),0) -> 964 | G26: =E26-F26 -> -0.39 | H26: =SUMPRODUCT(-$G$19:$G$27, VTM!I$2:I$10) -> -1.6928087 | I26: =F26+H26 -> 962.30719 | J26: =E26*30 -> 28908.3 | K26: =I26*31 -> 29831.523 | L26: =IF(J26=0,0,(K26-J26)/J26) -> 0.031936258 | M26: =J26*C13 -> 10369407 | N26: =K26*E13 -> 10700567 | O26: =N26-M26 -> 331160.07 | P26: =O26/N26 -> 0.030947898
A27: 10002013 | B27: IG Super 5 | C27: 1 Month | D27: =IF(E14=C14,IF(N14=L14,"No Change","Budget Change Only"),IF(N14=L14,"PTC Change Only","PTC + Others")) -> Budget Change Only | E27: 744.06 | F27: =ROUND(E27*((E14/C14)^L14)*((K14/J14)^N14)*((I14/H14)^M14),0) -> 744 | G27: =E27-F27 -> 0.06 | H27: =SUMPRODUCT(-$G$19:$G$27, VTM!J$2:J$10) -> -1.0695211 | I27: =F27+H27 -> 742.93048 | J27: =E27*30 -> 22321.8 | K27: =I27*31 -> 23030.845 | L27: =IF(J27=0,0,(K27-J27)/J27) -> 0.031764681 | M27: =J27*C14 -> 16636438 | N27: =K27*E14 -> 17164889 | O27: =N27-M27 -> 528451.12 | P27: =O27/N27 -> 0.030786749
B29: Assumptions & Formula
B30: SimUnits = currentunits * (simptc/currentptc)* (simposition/currentposition)^(-0.04) * EXP(0.03*(simosa-currentosa))
B31: Revenue = SimUnits * SimPTC
B32: Version 1.0: Volumes are anchored to recent actual sales and adjusted using estimated elasticities for Price, Budget, Position, and OSA. Calendar, seasonality, and festival effects are not currently included.
G43: 79 | H43: 84

Sheet Formula
B2: logy=alogx1+blogx2 | C2: y | D2: sim_vol | E2: 1497
B3: logy=log(x1^a*x2^b) | C3: a | D3: ptc_coeff | E3: -0.42
B4: y=x1^a*x2^b | C4: b | D4: budget_coeff | E4: 0.7
B5: y0= | C5: c | D5: osa coef | E5: 0.1
C6: d | D6: postion_coeff | E6: -0.1
C7: x1 | D7: ptc | E7: 365
C8: x2 | D8: budget | E8: 9000
C9: x3 | D9: osa | E9: 0.5
C10: x4 | D10: position | E10: 3.4

Sheet Model Reference
A1: OLS Model Reference — India Gate Everyday 5kg | Blinkit
A2: City Level | Day-level model
A4: Feature | B4: Coefficient | C4: Std Err | D4: z | E4: P>|z| | F4: Interpretation
A5: const | B5: 6.0655 | C5: 1.0159 | D5: 5.97 | E5: 0 | F5: Fixed intercept
A6: log_ptc | B6: -0.4246 | C6: 0.2053 | D6: -2.07 | E6: 0.039 | F6: Global price elasticity (cities vary via random slope)
A7: log_budget | B7: 0.13 | C7: 0.0126 | D7: 2.43 | E7: 0.015 | F7: Budget elasticity: +0.0306% vol per +1% budget
A8: Is_Weekend | B8: 0.0948 | C8: 0.0149 | D8: 6.37 | E8: 0 | F8: Weekend: +9.9% vs weekday
A9: Is_First_Week | B9: 0.1199 | C9: 0.0175 | D9: 6.84 | E9: 0 | F9: First week of month: +12.7%
A10: Event_Flag | B10: 0.0231 | C10: 0.0245 | D10: 0.94 | E10: 0.346 | F10: Event day: +2.3% (not significant)
A11: pre_event | B11: 0.0317 | C11: 0.0156 | D11: 2.03 | E11: 0.042 | F11: 3 days before event: +3.2%
A12: post_event | B12: -0.02 | C12: 0.0159 | D12: -1.26 | E12: 0.208 | F12: 3 days after event: -2.0% (not significant)
A13: log_qty_lag7 | B13: 0.1156 | C13: 0.0304 | D13: 3.81 | E13: 0 | F13: 7-day persistence: +0.116%
A14: log_avg_position | B14: -0.04 | C14: 0.0159 | D14: -1.26 | E14: 0.208 | F14: 3 days after event: -2.0% (not significant)
A15: OSA | B15: 0.03 | C15: 0.0304 | D15: 3.81 | E15: 0 | F15: 7-day persistence: +0.116%

Sheet Test Cases
A1: Test Scenario | B1: Input Change | C1: Expected Result | D1: Pass Criteria | E1: Passed/Failed
A2: No Change Baseline | B2: All simulated inputs = current inputs | C2: Simulated Units = Current Units | D2: Volume Δ = 0%, Revenue Δ = 0% | E2: Passed
A3: Price Increase +10% | B3: PTC +10% | C3: Units decrease by ~4.2% | D3: Simulated Units ≈ Current Units × 0.958 | E3: Passed
A4: Price Decrease -10% | B4: PTC -10% | C4: Units increase by ~4.2% | D4: Simulated Units ≈ Current Units × 1.042 | E4: Passed
A5: Budget Increase +20% | B5: Budget +20% | C5: Units increase by ~2.6% | D5: Volume Δ ≈ +2.6% | E5: Passed
A6: Budget Decrease -20% | B6: Budget -20% | C6: Units decrease by ~2.6% | D6: Volume Δ ≈ -2.6% | E6: Passed
A7: Position Improvement | B7: Avg Position 5.4 → 4.4 | C7: Units increase | D7: Volume Δ ≈ +0.82% | E7: Passed
A8: Position Deterioration | B8: Avg Position 5.4 → 6.4 | C8: Units decrease | D8: Volume Δ ≈ -0.68% | E8: Passed
A9: OSA Increase | B9: OSA 0.90 → 1.00 | C9: Slight unit increase | D9: Volume Δ ≈ +0.3% | E9: Passed
A10: OSA Decrease | B10: OSA 1.00 → 0.90 | C10: Slight unit decrease | D10: Volume Δ ≈ -0.3% | E10: Passed
A11: Combined Positive Scenario | B11: Price -5%, Budget +10%, Position +1 rank, OSA +5% | C11: Units increase | D11: Volume Δ > 0
A12: Combined Negative Scenario | B12: Price +10%, Budget -20%, Position worse, OSA lower | C12: Units decrease | D12: Volume Δ < 0
A13: Extreme Price Increase | B13: PTC +50% | C13: Units remain positive | D13: Units > 0
A14: Extreme Price Decrease | B14: PTC -50% | C14: No formula error | D14: Units > Current Units

Sheet VTM
B1: IG Everyday 5 | C1: IG Feast Rozzana 1 | D1: IG Feast Rozzana 5 | E1: IG Mini Mogra 10 | F1: IG Mini Mogra 5 | G1: IG Mini Mogra II 10 | H1: IG Mogra 10 | I1: IG Mogra 5 | J1: IG Super 5
A2: IG Everyday 5 | B2: 0 | C2: 0.075069112 | D2: 0.1166165 | E2: 0.0025436507 | F2: 0.013526457 | G2: 0.0094903446 | H2: 0.002381843 | I2: 0.016429978 | J2: 0.010718363
A3: IG Feast Rozzana 1 | B3: 0.093934578 | C3: 0 | D3: 0.079674619 | E3: 0.00057667415 | F3: 0.0038985816 | G3: 0.0020999728 | H3: 0.00053680766 | I3: 0.0045522704 | J3: 0.0028947782
A4: IG Feast Rozzana 5 | B4: 0.35133539 | C4: 0.19183051 | D4: 0 | E4: 0.0029641574 | F4: 0.014625579 | G4: 0.011112209 | H4: 0.0027579366 | I4: 0.018009864 | J4: 0.012170868
A5: IG Mini Mogra 10 | B5: 0.04452921 | C5: 0.0080677754 | D5: 0.017223717 | E5: 0 | F5: 0.30172558 | G5: 0.20518475 | H5: 0.062940933 | I5: 0.14555369 | J5: 0.014581552
A6: IG Mini Mogra 5 | B6: 0.075737797 | C6: 0.017445002 | D6: 0.027181898 | E6: 0.096505758 | F6: 0 | G6: 0.14007511 | H6: 0.035518947 | I6: 0.24961934 | J6: 0.01946265
A7: IG Mini Mogra II 10 | B7: 0.06951763 | C7: 0.012293129 | D7: 0.027017893 | E7: 0.085855978 | F7: 0.18325057 | G7: 0 | H7: 0.08004105 | I7: 0.22551197 | J7: 0.019714672
A8: IG Mogra 10 | B8: 0.042883626 | C8: 0.0077238329 | D8: 0.016481652 | E8: 0.064732745 | F8: 0.1142115 | G8: 0.19673344 | H8: 0 | I8: 0.34979633 | J8: 0.014986898
A9: IG Mogra 5 | B9: 0.080239059 | C9: 0.017766942 | D9: 0.029194255 | E9: 0.040605472 | F9: 0.21772007 | G9: 0.15035071 | H9: 0.094882416 | I9: 0 | J9: 0.020792533
A10: IG Super 5 | B10: 0.079569899 | C10: 0.017173998 | D10: 0.029990244 | E10: 0.0061835313 | F10: 0.025804395 | G10: 0.019980065 | H10: 0.0061795053 | I10: 0.03160668 | J10: 0
